[
    {
        "hero_id": 114,
        "last_played": 1724696643,
        "games": 107,
        "win": 46,
        "with_games": 17,
        "with_win": 9,
        "against_games": 20,
        "against_win": 12
    },
    {
        "hero_id": 81,
        "last_played": 1724693634,
        "games": 68,
        "win": 41,
        "with_games": 14,
        "with_win": 5,
        "against_games": 23,
        "against_win": 12
    },
    {
        "hero_id": 12,
        "last_played": 1722544311,
        "games": 63,
        "win": 36,
        "with_games": 12,
        "with_win": 5,
        "against_games": 35,
        "against_win": 20
    },
    {
        "hero_id": 8,
        "last_played": 1724616097,
        "games": 61,
        "win": 31,
        "with_games": 32,
        "with_win": 14,
        "against_games": 53,
        "against_win": 27
    },
    {
        "hero_id": 56,
        "last_played": 1721412762,
        "games": 57,
        "win": 35,
        "with_games": 14,
        "with_win": 8,
        "against_games": 22,
        "against_win": 8
    },
    {
        "hero_id": 4,
        "last_played": 1723650269,
        "games": 41,
        "win": 18,
        "with_games": 9,
        "with_win": 3,
        "against_games": 12,
        "against_win": 5
    },
    {
        "hero_id": 60,
        "last_played": 1724691023,
        "games": 38,
        "win": 15,
        "with_games": 13,
        "with_win": 9,
        "against_games": 13,
        "against_win": 8
    },
    {
        "hero_id": 102,
        "last_played": 1723135774,
        "games": 37,
        "win": 18,
        "with_games": 21,
        "with_win": 16,
        "against_games": 27,
        "against_win": 10
    },
    {
        "hero_id": 20,
        "last_played": 1723054182,
        "games": 34,
        "win": 16,
        "with_games": 44,
        "with_win": 21,
        "against_games": 61,
        "against_win": 22
    },
    {
        "hero_id": 28,
        "last_played": 1724612227,
        "games": 31,
        "win": 17,
        "with_games": 40,
        "with_win": 28,
        "against_games": 32,
        "against_win": 10
    },
    {
        "hero_id": 47,
        "last_played": 1723059267,
        "games": 20,
        "win": 7,
        "with_games": 24,
        "with_win": 9,
        "against_games": 26,
        "against_win": 10
    },
    {
        "hero_id": 48,
        "last_played": 1723485552,
        "games": 20,
        "win": 8,
        "with_games": 15,
        "with_win": 7,
        "against_games": 24,
        "against_win": 9
    },
    {
        "hero_id": 6,
        "last_played": 1723148236,
        "games": 15,
        "win": 4,
        "with_games": 41,
        "with_win": 18,
        "against_games": 53,
        "against_win": 20
    },
    {
        "hero_id": 49,
        "last_played": 1723063027,
        "games": 15,
        "win": 7,
        "with_games": 27,
        "with_win": 14,
        "against_games": 23,
        "against_win": 9
    },
    {
        "hero_id": 42,
        "last_played": 1723746556,
        "games": 9,
        "win": 3,
        "with_games": 28,
        "with_win": 16,
        "against_games": 50,
        "against_win": 22
    },
    {
        "hero_id": 104,
        "last_played": 1717531291,
        "games": 9,
        "win": 3,
        "with_games": 32,
        "with_win": 16,
        "against_games": 49,
        "against_win": 27
    },
    {
        "hero_id": 51,
        "last_played": 1724703565,
        "games": 8,
        "win": 5,
        "with_games": 10,
        "with_win": 3,
        "against_games": 10,
        "against_win": 7
    },
    {
        "hero_id": 121,
        "last_played": 1723661829,
        "games": 6,
        "win": 5,
        "with_games": 28,
        "with_win": 15,
        "against_games": 34,
        "against_win": 17
    },
    {
        "hero_id": 31,
        "last_played": 1714572497,
        "games": 4,
        "win": 3,
        "with_games": 48,
        "with_win": 27,
        "against_games": 40,
        "against_win": 20
    },
    {
        "hero_id": 37,
        "last_played": 1718455230,
        "games": 4,
        "win": 0,
        "with_games": 35,
        "with_win": 16,
        "against_games": 45,
        "against_win": 16
    },
    {
        "hero_id": 44,
        "last_played": 1723753361,
        "games": 4,
        "win": 1,
        "with_games": 27,
        "with_win": 11,
        "against_games": 58,
        "against_win": 25
    },
    {
        "hero_id": 69,
        "last_played": 1709328711,
        "games": 4,
        "win": 4,
        "with_games": 3,
        "with_win": 1,
        "against_games": 10,
        "against_win": 6
    },
    {
        "hero_id": 123,
        "last_played": 1723495312,
        "games": 4,
        "win": 3,
        "with_games": 63,
        "with_win": 31,
        "against_games": 41,
        "against_win": 20
    },
    {
        "hero_id": 129,
        "last_played": 1722972232,
        "games": 4,
        "win": 1,
        "with_games": 21,
        "with_win": 8,
        "against_games": 21,
        "against_win": 11
    },
    {
        "hero_id": 18,
        "last_played": 1696361850,
        "games": 3,
        "win": 0,
        "with_games": 9,
        "with_win": 1,
        "against_games": 28,
        "against_win": 15
    },
    {
        "hero_id": 87,
        "last_played": 1712872662,
        "games": 3,
        "win": 1,
        "with_games": 28,
        "with_win": 12,
        "against_games": 33,
        "against_win": 16
    },
    {
        "hero_id": 27,
        "last_played": 1717608979,
        "games": 2,
        "win": 2,
        "with_games": 59,
        "with_win": 29,
        "against_games": 52,
        "against_win": 26
    },
    {
        "hero_id": 30,
        "last_played": 1696171675,
        "games": 2,
        "win": 0,
        "with_games": 112,
        "with_win": 57,
        "against_games": 81,
        "against_win": 41
    },
    {
        "hero_id": 41,
        "last_played": 1714409130,
        "games": 2,
        "win": 1,
        "with_games": 26,
        "with_win": 16,
        "against_games": 46,
        "against_win": 24
    },
    {
        "hero_id": 54,
        "last_played": 1719256284,
        "games": 2,
        "win": 0,
        "with_games": 25,
        "with_win": 11,
        "against_games": 35,
        "against_win": 14
    },
    {
        "hero_id": 59,
        "last_played": 1693850457,
        "games": 2,
        "win": 1,
        "with_games": 9,
        "with_win": 2,
        "against_games": 18,
        "against_win": 11
    },
    {
        "hero_id": 70,
        "last_played": 1722537486,
        "games": 2,
        "win": 0,
        "with_games": 22,
        "with_win": 9,
        "against_games": 37,
        "against_win": 23
    },
    {
        "hero_id": 93,
        "last_played": 1708900073,
        "games": 2,
        "win": 1,
        "with_games": 20,
        "with_win": 11,
        "against_games": 34,
        "against_win": 19
    },
    {
        "hero_id": 23,
        "last_played": 1713980383,
        "games": 1,
        "win": 0,
        "with_games": 23,
        "with_win": 12,
        "against_games": 30,
        "against_win": 14
    },
    {
        "hero_id": 26,
        "last_played": 1705578084,
        "games": 1,
        "win": 1,
        "with_games": 66,
        "with_win": 23,
        "against_games": 82,
        "against_win": 39
    },
    {
        "hero_id": 35,
        "last_played": 1714590174,
        "games": 1,
        "win": 1,
        "with_games": 80,
        "with_win": 44,
        "against_games": 69,
        "against_win": 30
    },
    {
        "hero_id": 50,
        "last_played": 1695831249,
        "games": 1,
        "win": 0,
        "with_games": 35,
        "with_win": 19,
        "against_games": 52,
        "against_win": 30
    },
    {
        "hero_id": 57,
        "last_played": 1713976145,
        "games": 1,
        "win": 1,
        "with_games": 8,
        "with_win": 3,
        "against_games": 15,
        "against_win": 5
    },
    {
        "hero_id": 63,
        "last_played": 1718452734,
        "games": 1,
        "win": 0,
        "with_games": 18,
        "with_win": 6,
        "against_games": 25,
        "against_win": 11
    },
    {
        "hero_id": 64,
        "last_played": 1718046982,
        "games": 1,
        "win": 1,
        "with_games": 48,
        "with_win": 22,
        "against_games": 43,
        "against_win": 16
    },
    {
        "hero_id": 79,
        "last_played": 1695752422,
        "games": 1,
        "win": 0,
        "with_games": 7,
        "with_win": 2,
        "against_games": 9,
        "against_win": 5
    },
    {
        "hero_id": 92,
        "last_played": 1713985868,
        "games": 1,
        "win": 0,
        "with_games": 2,
        "with_win": 0,
        "against_games": 2,
        "against_win": 1
    },
    {
        "hero_id": 94,
        "last_played": 1697053337,
        "games": 1,
        "win": 0,
        "with_games": 15,
        "with_win": 9,
        "against_games": 20,
        "against_win": 10
    },
    {
        "hero_id": 96,
        "last_played": 1696194059,
        "games": 1,
        "win": 0,
        "with_games": 18,
        "with_win": 8,
        "against_games": 23,
        "against_win": 13
    },
    {
        "hero_id": 99,
        "last_played": 1697367131,
        "games": 1,
        "win": 0,
        "with_games": 30,
        "with_win": 8,
        "against_games": 33,
        "against_win": 13
    },
    {
        "hero_id": 112,
        "last_played": 1713989814,
        "games": 1,
        "win": 0,
        "with_games": 21,
        "with_win": 11,
        "against_games": 11,
        "against_win": 5
    },
    {
        "hero_id": 113,
        "last_played": 1714419180,
        "games": 1,
        "win": 1,
        "with_games": 4,
        "with_win": 3,
        "against_games": 20,
        "against_win": 9
    },
    {
        "hero_id": 119,
        "last_played": 1696245055,
        "games": 1,
        "win": 0,
        "with_games": 21,
        "with_win": 14,
        "against_games": 24,
        "against_win": 11
    },
    {
        "hero_id": 1,
        "last_played": 0,
        "games": 0,
        "win": 0,
        "with_games": 21,
        "with_win": 11,
        "against_games": 32,
        "against_win": 12
    },
    {
        "hero_id": 2,
        "last_played": 0,
        "games": 0,
        "win": 0,
        "with_games": 74,
        "with_win": 42,
        "against_games": 78,
        "against_win": 30
    },
    {
        "hero_id": 3,
        "last_played": 0,
        "games": 0,
        "win": 0,
        "with_games": 8,
        "with_win": 3,
        "against_games": 8,
        "against_win": 5
    },
    {
        "hero_id": 5,
        "last_played": 0,
        "games": 0,
        "win": 0,
        "with_games": 50,
        "with_win": 23,
        "against_games": 45,
        "against_win": 21
    },
    {
        "hero_id": 7,
        "last_played": 0,
        "games": 0,
        "win": 0,
        "with_games": 26,
        "with_win": 14,
        "against_games": 43,
        "against_win": 21
    },
    {
        "hero_id": 9,
        "last_played": 0,
        "games": 0,
        "win": 0,
        "with_games": 26,
        "with_win": 12,
        "against_games": 23,
        "against_win": 16
    },
    {
        "hero_id": 10,
        "last_played": 0,
        "games": 0,
        "win": 0,
        "with_games": 12,
        "with_win": 5,
        "against_games": 20,
        "against_win": 15
    },
    {
        "hero_id": 11,
        "last_played": 0,
        "games": 0,
        "win": 0,
        "with_games": 27,
        "with_win": 17,
        "against_games": 49,
        "against_win": 19
    },
    {
        "hero_id": 13,
        "last_played": 0,
        "games": 0,
        "win": 0,
        "with_games": 13,
        "with_win": 5,
        "against_games": 25,
        "against_win": 17
    },
    {
        "hero_id": 14,
        "last_played": 0,
        "games": 0,
        "win": 0,
        "with_games": 79,
        "with_win": 36,
        "against_games": 124,
        "against_win": 60
    },
    {
        "hero_id": 15,
        "last_played": 0,
        "games": 0,
        "win": 0,
        "with_games": 15,
        "with_win": 6,
        "against_games": 16,
        "against_win": 9
    },
    {
        "hero_id": 16,
        "last_played": 0,
        "games": 0,
        "win": 0,
        "with_games": 17,
        "with_win": 5,
        "against_games": 28,
        "against_win": 16
    },
    {
        "hero_id": 17,
        "last_played": 0,
        "games": 0,
        "win": 0,
        "with_games": 26,
        "with_win": 12,
        "against_games": 24,
        "against_win": 11
    },
    {
        "hero_id": 19,
        "last_played": 0,
        "games": 0,
        "win": 0,
        "with_games": 6,
        "with_win": 3,
        "against_games": 17,
        "against_win": 7
    },
    {
        "hero_id": 21,
        "last_played": 0,
        "games": 0,
        "win": 0,
        "with_games": 31,
        "with_win": 12,
        "against_games": 29,
        "against_win": 15
    },
    {
        "hero_id": 22,
        "last_played": 0,
        "games": 0,
        "win": 0,
        "with_games": 46,
        "with_win": 24,
        "against_games": 55,
        "against_win": 27
    },
    {
        "hero_id": 25,
        "last_played": 0,
        "games": 0,
        "win": 0,
        "with_games": 28,
        "with_win": 11,
        "against_games": 53,
        "against_win": 26
    },
    {
        "hero_id": 29,
        "last_played": 0,
        "games": 0,
        "win": 0,
        "with_games": 20,
        "with_win": 12,
        "against_games": 10,
        "against_win": 8
    },
    {
        "hero_id": 32,
        "last_played": 0,
        "games": 0,
        "win": 0,
        "with_games": 15,
        "with_win": 5,
        "against_games": 26,
        "against_win": 9
    },
    {
        "hero_id": 33,
        "last_played": 0,
        "games": 0,
        "win": 0,
        "with_games": 5,
        "with_win": 1,
        "against_games": 9,
        "against_win": 5
    },
    {
        "hero_id": 34,
        "last_played": 0,
        "games": 0,
        "win": 0,
        "with_games": 4,
        "with_win": 3,
        "against_games": 18,
        "against_win": 10
    },
    {
        "hero_id": 36,
        "last_played": 0,
        "games": 0,
        "win": 0,
        "with_games": 38,
        "with_win": 21,
        "against_games": 35,
        "against_win": 17
    },
    {
        "hero_id": 38,
        "last_played": 0,
        "games": 0,
        "win": 0,
        "with_games": 3,
        "with_win": 2,
        "against_games": 3,
        "against_win": 3
    },
    {
        "hero_id": 39,
        "last_played": 0,
        "games": 0,
        "win": 0,
        "with_games": 24,
        "with_win": 11,
        "against_games": 22,
        "against_win": 13
    },
    {
        "hero_id": 40,
        "last_played": 0,
        "games": 0,
        "win": 0,
        "with_games": 36,
        "with_win": 21,
        "against_games": 28,
        "against_win": 15
    },
    {
        "hero_id": 43,
        "last_played": 0,
        "games": 0,
        "win": 0,
        "with_games": 7,
        "with_win": 5,
        "against_games": 10,
        "against_win": 5
    },
    {
        "hero_id": 45,
        "last_played": 0,
        "games": 0,
        "win": 0,
        "with_games": 15,
        "with_win": 5,
        "against_games": 18,
        "against_win": 8
    },
    {
        "hero_id": 46,
        "last_played": 0,
        "games": 0,
        "win": 0,
        "with_games": 13,
        "with_win": 8,
        "against_games": 22,
        "against_win": 12
    },
    {
        "hero_id": 52,
        "last_played": 0,
        "games": 0,
        "win": 0,
        "with_games": 17,
        "with_win": 5,
        "against_games": 8,
        "against_win": 2
    },
    {
        "hero_id": 53,
        "last_played": 0,
        "games": 0,
        "win": 0,
        "with_games": 42,
        "with_win": 10,
        "against_games": 42,
        "against_win": 20
    },
    {
        "hero_id": 55,
        "last_played": 0,
        "games": 0,
        "win": 0,
        "with_games": 7,
        "with_win": 6,
        "against_games": 5,
        "against_win": 1
    },
    {
        "hero_id": 58,
        "last_played": 0,
        "games": 0,
        "win": 0,
        "with_games": 11,
        "with_win": 5,
        "against_games": 18,
        "against_win": 10
    },
    {
        "hero_id": 61,
        "last_played": 0,
        "games": 0,
        "win": 0,
        "with_games": 0,
        "with_win": 0,
        "against_games": 6,
        "against_win": 4
    },
    {
        "hero_id": 62,
        "last_played": 0,
        "games": 0,
        "win": 0,
        "with_games": 16,
        "with_win": 8,
        "against_games": 27,
        "against_win": 18
    },
    {
        "hero_id": 65,
        "last_played": 0,
        "games": 0,
        "win": 0,
        "with_games": 3,
        "with_win": 2,
        "against_games": 3,
        "against_win": 1
    },
    {
        "hero_id": 66,
        "last_played": 0,
        "games": 0,
        "win": 0,
        "with_games": 3,
        "with_win": 1,
        "against_games": 1,
        "against_win": 0
    },
    {
        "hero_id": 67,
        "last_played": 0,
        "games": 0,
        "win": 0,
        "with_games": 25,
        "with_win": 10,
        "against_games": 42,
        "against_win": 24
    },
    {
        "hero_id": 68,
        "last_played": 0,
        "games": 0,
        "win": 0,
        "with_games": 31,
        "with_win": 16,
        "against_games": 45,
        "against_win": 24
    },
    {
        "hero_id": 71,
        "last_played": 0,
        "games": 0,
        "win": 0,
        "with_games": 36,
        "with_win": 22,
        "against_games": 56,
        "against_win": 22
    },
    {
        "hero_id": 72,
        "last_played": 0,
        "games": 0,
        "win": 0,
        "with_games": 15,
        "with_win": 6,
        "against_games": 22,
        "against_win": 10
    },
    {
        "hero_id": 73,
        "last_played": 0,
        "games": 0,
        "win": 0,
        "with_games": 9,
        "with_win": 4,
        "against_games": 10,
        "against_win": 6
    },
    {
        "hero_id": 74,
        "last_played": 0,
        "games": 0,
        "win": 0,
        "with_games": 39,
        "with_win": 14,
        "against_games": 56,
        "against_win": 33
    },
    {
        "hero_id": 75,
        "last_played": 0,
        "games": 0,
        "win": 0,
        "with_games": 33,
        "with_win": 15,
        "against_games": 42,
        "against_win": 22
    },
    {
        "hero_id": 76,
        "last_played": 0,
        "games": 0,
        "win": 0,
        "with_games": 24,
        "with_win": 10,
        "against_games": 39,
        "against_win": 16
    },
    {
        "hero_id": 77,
        "last_played": 0,
        "games": 0,
        "win": 0,
        "with_games": 4,
        "with_win": 1,
        "against_games": 11,
        "against_win": 4
    },
    {
        "hero_id": 78,
        "last_played": 0,
        "games": 0,
        "win": 0,
        "with_games": 4,
        "with_win": 3,
        "against_games": 8,
        "against_win": 6
    },
    {
        "hero_id": 80,
        "last_played": 0,
        "games": 0,
        "win": 0,
        "with_games": 15,
        "with_win": 7,
        "against_games": 8,
        "against_win": 3
    },
    {
        "hero_id": 82,
        "last_played": 0,
        "games": 0,
        "win": 0,
        "with_games": 3,
        "with_win": 0,
        "against_games": 5,
        "against_win": 2
    },
    {
        "hero_id": 83,
        "last_played": 0,
        "games": 0,
        "win": 0,
        "with_games": 24,
        "with_win": 13,
        "against_games": 20,
        "against_win": 14
    },
    {
        "hero_id": 84,
        "last_played": 0,
        "games": 0,
        "win": 0,
        "with_games": 45,
        "with_win": 22,
        "against_games": 49,
        "against_win": 23
    },
    {
        "hero_id": 85,
        "last_played": 0,
        "games": 0,
        "win": 0,
        "with_games": 27,
        "with_win": 16,
        "against_games": 33,
        "against_win": 11
    },
    {
        "hero_id": 86,
        "last_played": 0,
        "games": 0,
        "win": 0,
        "with_games": 36,
        "with_win": 15,
        "against_games": 58,
        "against_win": 28
    },
    {
        "hero_id": 88,
        "last_played": 0,
        "games": 0,
        "win": 0,
        "with_games": 9,
        "with_win": 5,
        "against_games": 27,
        "against_win": 12
    },
    {
        "hero_id": 89,
        "last_played": 0,
        "games": 0,
        "win": 0,
        "with_games": 7,
        "with_win": 2,
        "against_games": 1,
        "against_win": 1
    },
    {
        "hero_id": 90,
        "last_played": 0,
        "games": 0,
        "win": 0,
        "with_games": 5,
        "with_win": 2,
        "against_games": 18,
        "against_win": 11
    },
    {
        "hero_id": 91,
        "last_played": 0,
        "games": 0,
        "win": 0,
        "with_games": 6,
        "with_win": 5,
        "against_games": 14,
        "against_win": 7
    },
    {
        "hero_id": 95,
        "last_played": 0,
        "games": 0,
        "win": 0,
        "with_games": 19,
        "with_win": 11,
        "against_games": 19,
        "against_win": 10
    },
    {
        "hero_id": 97,
        "last_played": 0,
        "games": 0,
        "win": 0,
        "with_games": 19,
        "with_win": 11,
        "against_games": 24,
        "against_win": 11
    },
    {
        "hero_id": 98,
        "last_played": 0,
        "games": 0,
        "win": 0,
        "with_games": 13,
        "with_win": 3,
        "against_games": 26,
        "against_win": 19
    },
    {
        "hero_id": 100,
        "last_played": 0,
        "games": 0,
        "win": 0,
        "with_games": 8,
        "with_win": 2,
        "against_games": 19,
        "against_win": 9
    },
    {
        "hero_id": 101,
        "last_played": 0,
        "games": 0,
        "win": 0,
        "with_games": 23,
        "with_win": 9,
        "against_games": 27,
        "against_win": 13
    },
    {
        "hero_id": 103,
        "last_played": 0,
        "games": 0,
        "win": 0,
        "with_games": 2,
        "with_win": 1,
        "against_games": 4,
        "against_win": 3
    },
    {
        "hero_id": 105,
        "last_played": 0,
        "games": 0,
        "win": 0,
        "with_games": 19,
        "with_win": 9,
        "against_games": 23,
        "against_win": 12
    },
    {
        "hero_id": 106,
        "last_played": 0,
        "games": 0,
        "win": 0,
        "with_games": 21,
        "with_win": 9,
        "against_games": 18,
        "against_win": 8
    },
    {
        "hero_id": 107,
        "last_played": 0,
        "games": 0,
        "win": 0,
        "with_games": 24,
        "with_win": 13,
        "against_games": 12,
        "against_win": 6
    },
    {
        "hero_id": 108,
        "last_played": 0,
        "games": 0,
        "win": 0,
        "with_games": 8,
        "with_win": 5,
        "against_games": 7,
        "against_win": 5
    },
    {
        "hero_id": 109,
        "last_played": 0,
        "games": 0,
        "win": 0,
        "with_games": 3,
        "with_win": 2,
        "against_games": 4,
        "against_win": 2
    },
    {
        "hero_id": 110,
        "last_played": 0,
        "games": 0,
        "win": 0,
        "with_games": 22,
        "with_win": 15,
        "against_games": 11,
        "against_win": 2
    },
    {
        "hero_id": 111,
        "last_played": 0,
        "games": 0,
        "win": 0,
        "with_games": 19,
        "with_win": 15,
        "against_games": 18,
        "against_win": 7
    },
    {
        "hero_id": 120,
        "last_played": 0,
        "games": 0,
        "win": 0,
        "with_games": 6,
        "with_win": 4,
        "against_games": 8,
        "against_win": 4
    },
    {
        "hero_id": 126,
        "last_played": 0,
        "games": 0,
        "win": 0,
        "with_games": 16,
        "with_win": 7,
        "against_games": 18,
        "against_win": 7
    },
    {
        "hero_id": 128,
        "last_played": 0,
        "games": 0,
        "win": 0,
        "with_games": 15,
        "with_win": 8,
        "against_games": 20,
        "against_win": 11
    },
    {
        "hero_id": 131,
        "last_played": 0,
        "games": 0,
        "win": 0,
        "with_games": 2,
        "with_win": 0,
        "against_games": 0,
        "against_win": 0
    },
    {
        "hero_id": 135,
        "last_played": 0,
        "games": 0,
        "win": 0,
        "with_games": 10,
        "with_win": 5,
        "against_games": 24,
        "against_win": 10
    },
    {
        "hero_id": 136,
        "last_played": 0,
        "games": 0,
        "win": 0,
        "with_games": 7,
        "with_win": 3,
        "against_games": 13,
        "against_win": 6
    },
    {
        "hero_id": 137,
        "last_played": 0,
        "games": 0,
        "win": 0,
        "with_games": 14,
        "with_win": 8,
        "against_games": 19,
        "against_win": 10
    },
    {
        "hero_id": 138,
        "last_played": 0,
        "games": 0,
        "win": 0,
        "with_games": 17,
        "with_win": 10,
        "against_games": 28,
        "against_win": 14
    }
]